{"stem":"augenblick","instances":[{"docId":"amp-transcript__0053","docUri":"amp-transcript__0053.html","score":1,"contexts":[{"form":"Augenblick","weight":"1","pos":965,"context":"...die Prinzessin Anne geehrbt. Daß Deine Haut im <mark>Augenblick<\/mark> kin keinem guten Zustand ist, ist sehr ärgerlich...","fid":"text-resize-2"}]},{"docId":"amp-transcript__0039","docUri":"amp-transcript__0039.html","score":1,"contexts":[{"form":"Augenblick","weight":"1","pos":307,"context":"...Stunde deines Todes,unbegrüsst von dir war der <mark>Augenblick<\/mark>,als ich,von der Vorsehung geleitet,...","fid":"text-resize-5"}]}]}