{"stem":"noch","instances":[{"docId":"amp-transcript__0053","docUri":"amp-transcript__0053.html","score":4,"contexts":[{"form":"noch","weight":"1","pos":31,"context":"...nicht viel davon.      Heute stehe ich immer <mark>noch<\/mark> unter dem Eindruck des gestirrigen Ausflugs nach Kirchstetten wohin...","fid":"text-resize-1"},{"form":"noch","weight":"1","pos":476,"context":"...denie Mitmenschen der Fall ist.  \"Ich bin <mark>noch<\/mark> immer das verschreckte, verheulte Kind, das sich irgendwie...","fid":"text-resize-2"},{"form":"noch","weight":"1","pos":582,"context":"...sprach über diesen uralten Kulturboden, \"wo die Leute <mark>noch<\/mark> heute Sachen tun, die vier, fünf Jahrtausende...","fid":"text-resize-2"},{"form":"noch","weight":"1","pos":860,"context":"...es\". Jetzt will ich Deine Fragen beantworten und sonst <mark>noch<\/mark> schauen was in Deinem letzten Brief steht.  ...","fid":"text-resize-2"}]},{"docId":"amp-transcript__0039","docUri":"amp-transcript__0039.html","score":2,"contexts":[{"form":"noch","weight":"1","pos":404,"context":"...gerückt war. Bis jezt jetzt ist die Erde <mark>noch<\/mark> nie ohne ihren faulen Stellen,einen Unort mit...","fid":"text-resize-5"},{"form":"noch","weight":"1","pos":425,"context":"    <mark>noch<\/mark> nie war überall Frieden auf ihrer nährenden Oberfläche:...","fid":"text-resize-5"}]}]}