{"stem":"zum","instances":[{"docId":"amp-transcript__0039","docUri":"amp-transcript__0039.html","score":1,"contexts":[{"form":"zum","weight":"1","pos":490,"context":"...kennen,von des Aprils rasch zunehmenden Farbtönen bis <mark>zum<\/mark> ungestümen Herbst, wann bei jedem stotternden Windstoss Äpfel...","fid":"text-resize-5"}]},{"docId":"amp-transcript__0058","docUri":"amp-transcript__0058.html","score":1,"contexts":[{"form":"zum","weight":"1","pos":6,"context":" Können Sie Mittwoch anstatt Donnerstag <mark>zum<\/mark> Abendessen kommen ","fid":"text-resize-1"}]}]}